strsimpy/__init__.py
strsimpy/cosine.py
strsimpy/cosine_test.py
strsimpy/damerau.py
strsimpy/damerau_test.py
strsimpy/jaccard.py
strsimpy/jaccard_test.py
strsimpy/jaro_winkler.py
strsimpy/jaro_winkler_test.py
strsimpy/levenshtein.py
strsimpy/levenshtein_test.py
strsimpy/longest_common_subsequence.py
strsimpy/longest_common_subsequence_test.py
strsimpy/metric_lcs.py
strsimpy/metric_lcs_test.py
strsimpy/ngram.py
strsimpy/ngram_test.py
strsimpy/normalized_levenshtein.py
strsimpy/normalized_levenshtein_test.py
strsimpy/optimal_string_alignment.py
strsimpy/optimal_string_alignment_test.py
strsimpy/overlap_coefficient.py
strsimpy/overlap_coefficient_test.py
strsimpy/qgram.py
strsimpy/qgram_test.py
strsimpy/shingle_based.py
strsimpy/sift4.py
strsimpy/sift4_test.py
strsimpy/sorensen_dice.py
strsimpy/sorensen_dice_test.py
strsimpy/string_distance.py
strsimpy/string_similarity.py
strsimpy/weighted_levenshtein.py
strsimpy/weighted_levenshtein_test.py
strsimpy-0.2.1.dist-info/LICENSE
strsimpy-0.2.1.dist-info/METADATA
strsimpy-0.2.1.dist-info/WHEEL
strsimpy-0.2.1.dist-info/top_level.txt
strsimpy-0.2.1.dist-info/RECORD
