Metadata-Version: 2.1
Name: strsimpy
Version: 0.2.1
Summary: A library implementing different string similarity and distance measures
Home-page: https://github.com/luozhouyang/python-string-similarity
Author: ZhouYang Luo
Author-email: zhouyang.luo@gmail.com
License: MIT License
Platform: UNKNOWN
Classifier: Programming Language :: Python :: 3
Classifier: Programming Language :: Python :: 3.5
Classifier: Programming Language :: Python :: 3.6
Classifier: Programming Language :: Python :: 3.7
Classifier: Programming Language :: Python :: 3.8
Classifier: Programming Language :: Python :: 3.9
Classifier: License :: OSI Approved :: MIT License
Classifier: Operating System :: OS Independent
